cache_controller.v

module fsm(
    input clk,
    input rst,
    input read,
    input write,
    input hit,
    input memory_ready,               
    input [31:0] address,             
    input [31:0] data_from_CPU,       
    output reg memory_req,            
    output reg cpu_ready,               
    output reg [31:0] data_to_CPU     
);

    // here I define the states of the finite state machine
    // each state represents one step in the cache operation
    localparam ST_IDLE       = 4'b0000; // waits for a read or write request
    localparam ST_COMPARE    = 4'b0001; // checks if the address is already in cache
    localparam ST_READ_HIT   = 4'b0010; // successful read directly from cache
    localparam ST_READ_MISS  = 4'b0011; // read after the data has been brought into cache
    localparam ST_WRITE_HIT  = 4'b0100; // write directly into cache because there is a hit
    localparam ST_WRITE_MISS = 4'b0101; // write after the line has been brought into cache
    localparam ST_WRITE_BACK = 4'b0110; // writes back to memory if the line is dirty
    localparam ST_EVICT      = 4'b0111; // removes the old line from cache
    localparam ST_ALLOCATE   = 4'b1000; // brings a new line from memory into cache
    
    // current state and next state
    reg [3:0] st;        
    reg [3:0] st_next;   
    
    // each cache line has a dirty bit
    // dirty = 1 means that the line was modified and must be saved to memory
    reg dirty_mem [0:1];           
    
    // the cache has 2 lines, each line having 32 bits
    reg [31:0] cache_mem [0:1]; 
    
    // I use bit 2 from the address as index
    // because I only have 2 cache lines, the index can be 0 or 1
    wire idx = address[2]; 

    // here I update the FSM state and the dirty bit
    always @ (posedge clk or posedge rst) begin
        if(rst) begin
            // on reset, the FSM starts from the IDLE state
            // and the cache lines are considered clean
            st <= ST_IDLE; 
            dirty_mem[0] <= 1'b0;
            dirty_mem[1] <= 1'b0;
        end
        else begin
            // on each positive clock edge, I move to the next state
            st <= st_next;
            
            // if a write was performed, that line becomes dirty
            // meaning it was modified in cache compared to main memory
            if(st_next == ST_WRITE_HIT || st_next == ST_WRITE_MISS) 
                dirty_mem[idx] <= 1'b1;

            // after the line has been evicted, it is no longer dirty
            else if(st_next == ST_EVICT) 
                dirty_mem[idx] <= 1'b0;
        end 
    end
  
    // here is the main FSM logic
    // depending on the current state and signals, I choose the next state
    always @ (*) begin
        // by default, I remain in the same state
        st_next = st;

        case(st)

            ST_IDLE: begin
                // the FSM stays here until the CPU requests a read or write
                if(read || write) 
                    st_next = ST_COMPARE;
            end
            
            ST_COMPARE: begin
                // if we have a hit, it means the data is already in cache
                if(hit) begin 
                    if(read)       
                        st_next = ST_READ_HIT;
                    else if(write) 
                        st_next = ST_WRITE_HIT;
                end
                else begin 
                    // if we have a miss, we must check if the old line is dirty
                    // if it is dirty, it must first be written back to memory
                    if(dirty_mem[idx]) 
                        st_next = ST_WRITE_BACK;

                    // if it is not dirty, we can evict it directly
                    else               
                        st_next = ST_EVICT;
                end
            end
            
            ST_WRITE_BACK: begin
                // here we wait for memory to confirm that the write is complete
                if(memory_ready)   
                    st_next = ST_EVICT; 
                else               
                    st_next = ST_WRITE_BACK;
            end
            
            ST_EVICT: begin
                // after freeing the line, we can bring the new data
                st_next = ST_ALLOCATE;
            end
            
            ST_ALLOCATE: begin
                // here we wait for memory to send the data for the new line
                if(memory_ready) begin 
                    // after allocation, we go to read miss or write miss,
                    // depending on the initial request
                    if(read)       
                        st_next = ST_READ_MISS;
                    else if(write) 
                        st_next = ST_WRITE_MISS;
                end
                else begin
                    // if memory is not ready, we remain here
                    st_next = ST_ALLOCATE;
                end
            end
            
            // these states are final for the current operation
            // after the operation is finished, we return to IDLE
            ST_READ_HIT, ST_WRITE_HIT, ST_READ_MISS, ST_WRITE_MISS: begin
                st_next = ST_IDLE;
            end

            // if an unknown state appears, I return to IDLE as protection
            default: begin
                st_next = ST_IDLE;
            end
        endcase
    end

    // here I actually update the cache content
    always @ (posedge clk or posedge rst) begin
        if(rst) begin
            // on reset I put some initial values, just so we have something in cache
            cache_mem[0] <= 32'h11112222; 
            cache_mem[1] <= 32'h33334444; 
        end
        else begin
            // if we have write hit or write miss, I write the data from the CPU into cache
            if(st == ST_WRITE_HIT || st == ST_WRITE_MISS) begin
                cache_mem[idx] <= data_from_CPU;
            end

            // if we have allocate and memory is ready,
            // I simulate bringing a new line from memory
            else if(st == ST_ALLOCATE && memory_ready) begin
                cache_mem[idx] <= (idx == 0) ? 32'hABCDEFFF : 32'h99999999; 
            end
        end
    end

    // here I generate the FSM outputs
    always @ (*) begin
        // default values, to avoid latches
        cpu_ready = 1'b0;
        memory_req = 1'b0;
        data_to_CPU = 32'h0;

        case(st)

            // in these states I need to communicate with main memory
            // either for write-back or for bringing a new line
            ST_WRITE_BACK: begin
                memory_req = 1'b1;
            end

            ST_ALLOCATE: begin
                memory_req = 1'b1;
            end
            
            // on read, I send the value from cache to the CPU
            // and activate cpu_ready because the operation is finished
            ST_READ_HIT, ST_READ_MISS: begin
                data_to_CPU = cache_mem[idx];
                cpu_ready = 1'b1;
            end
            
            // on write, I do not need to send data to the CPU,
            // I only announce that the write is finished
            ST_WRITE_HIT, ST_WRITE_MISS: begin
                cpu_ready = 1'b1;
            end
        endcase
    end
  
endmodule

testbench.v

module fsm_tb;
    reg clk, rst, read, write, hit, memory_ready;
    reg [31:0] address;
    reg [31:0] data_from_CPU;
    
    wire cpu_ready;
    wire [31:0] data_to_CPU;
    wire memory_req;
    wire [3:0] st; 
     
    fsm uut (
        .clk(clk),
        .rst(rst),
        .read(read),
        .write(write),
        .hit(hit),
        .memory_ready(memory_ready),
        .address(address),
        .data_from_CPU(data_from_CPU),
        .memory_req(memory_req),
        .cpu_ready(cpu_ready),
        .data_to_CPU(data_to_CPU)
    );
    
    // used to make the current state visible in the waveform
    assign st = uut.st;
     
    always #10 clk = ~clk;

    // used to make the cache lines and dirty bits visible in the waveform
    wire [31:0] cache_line_0 = uut.cache_mem[0];
    wire [31:0] cache_line_1 = uut.cache_mem[1];
    wire dirty_line_0 = uut.dirty_mem[0];
    wire dirty_line_1 = uut.dirty_mem[1];
    
    // task used to display the state names, making the simulation easier to follow
    task print_state;
        begin 
            case(st) 
                4'b0000: $write("IDLE");
                4'b0001: $write("COMPARE");
                4'b0010: $write("READ_HIT");
                4'b0011: $write("READ_MISS");
                4'b0100: $write("WRITE_HIT");
                4'b0101: $write("WRITE_MISS");
                4'b0110: $write("WRITE_BACK");
                4'b0111: $write("EVICT");
                4'b1000: $write("ALLOCATE");
                default: $write("UNKNOWN");
            endcase

            $write("(dirty=%b, cpu_ready=%b) ", uut.dirty_mem[uut.idx], cpu_ready);
        end
    endtask
    
    task run_fsm;

        input task_read;
        input task_write;
        input task_hit; 
        input [31:0] task_addr;
        input [31:0] task_data;
        
        // stores the data returned by the cache during a read operation
        reg [31:0] captured_data;

        begin
            read          <= task_read;
            write         <= task_write;
            hit           <= task_hit;
            address       <= task_addr;
            data_from_CPU <= task_data;
            memory_ready  <= 1'b0;
           
            @(posedge clk);
            #1;
            print_state(); 
            
            // simulates the exchange between cache and RAM:
            // the cache sends a memory request, and RAM responds when ready
            // the while loop is used because we wait until the FSM returns to IDLE
            while (st != 4'b0000) begin
                if (memory_req) begin
                    #5;
                    memory_ready <= 1'b1;
                    #5;
                end
                
                // if the operation is a read, capture the data sent from cache to CPU              
                if (cpu_ready && task_read) begin
                    captured_data = data_to_CPU;
                end

                @(posedge clk); 
                #1;  
                print_state();  
                memory_ready <= 1'b0; 
            end
           
            // prints debug messages to check that everything works correctly
            if (task_read)
                $display("read at address %h: data to CPU = %h", task_addr, captured_data);
            else if (task_write)
                $display("write at adress %h: data saved in cache = %h", task_addr, task_data);

            read  <= 0;
            write <= 0;
            hit   <= 0;

            #1; 
        end
    endtask

    initial begin
        $dumpfile("dump.vcd");
        $dumpvars(0, fsm_tb);
        
        clk = 0;
        rst = 0;
        read = 0;
        write = 0;
        hit = 0;
        memory_ready = 0;
        address = 0;
        data_from_CPU = 0;
         
        #5  rst = 1;
        #20 rst = 0;
        #5; 
        
     
        $display("line 0 read hit");
        run_fsm(1, 0, 1, 32'h00002000, 32'h0); 

        $display("line 0 read miss");
        run_fsm(1, 0, 0, 32'h00002000, 32'h0); 
        
        $display("line 1 write hit 3");
        run_fsm(0, 1, 1, 32'h00002004, 32'hDEADBEEF); 

        $display("line 1 write miss 4: (write back , dirty=1) ");
        run_fsm(0, 1, 0, 32'hFFFF0004, 32'hCAFEAFFE); 

        $display("line 1 read hit (to see if the value is modified)");
        run_fsm(1, 0, 1, 32'hFFFF0004, 32'h0);

        $display("line 0 write miss (no need for write back)");
        run_fsm(0, 1, 0, 32'h00005000, 32'h12345678);

        $display("line 0 read hit");
        run_fsm(1, 0, 1, 32'h00005000, 32'h0);
        

        #100;
        $finish;
    end
endmodule

dump.vcd
$date
	Tue Jun  9 22:29:26 2026
$end
$version
	ModelSim Version 2021.1
$end
$timescale
	1ps
$end

$scope module fsm_tb $end
$var reg 1 ! clk $end
$var reg 1 " rst $end
$var reg 1 # read $end
$var reg 1 $ write $end
$var reg 1 % hit $end
$var reg 1 & memory_ready $end
$var reg 32 ' address [31:0] $end
$var reg 32 ( data_from_CPU [31:0] $end
$var wire 1 ) cpu_ready $end
$var wire 1 * data_to_CPU [31] $end
$var wire 1 + data_to_CPU [30] $end
$var wire 1 , data_to_CPU [29] $end
$var wire 1 - data_to_CPU [28] $end
$var wire 1 . data_to_CPU [27] $end
$var wire 1 / data_to_CPU [26] $end
$var wire 1 0 data_to_CPU [25] $end
$var wire 1 1 data_to_CPU [24] $end
$var wire 1 2 data_to_CPU [23] $end
$var wire 1 3 data_to_CPU [22] $end
$var wire 1 4 data_to_CPU [21] $end
$var wire 1 5 data_to_CPU [20] $end
$var wire 1 6 data_to_CPU [19] $end
$var wire 1 7 data_to_CPU [18] $end
$var wire 1 8 data_to_CPU [17] $end
$var wire 1 9 data_to_CPU [16] $end
$var wire 1 : data_to_CPU [15] $end
$var wire 1 ; data_to_CPU [14] $end
$var wire 1 < data_to_CPU [13] $end
$var wire 1 = data_to_CPU [12] $end
$var wire 1 > data_to_CPU [11] $end
$var wire 1 ? data_to_CPU [10] $end
$var wire 1 @ data_to_CPU [9] $end
$var wire 1 A data_to_CPU [8] $end
$var wire 1 B data_to_CPU [7] $end
$var wire 1 C data_to_CPU [6] $end
$var wire 1 D data_to_CPU [5] $end
$var wire 1 E data_to_CPU [4] $end
$var wire 1 F data_to_CPU [3] $end
$var wire 1 G data_to_CPU [2] $end
$var wire 1 H data_to_CPU [1] $end
$var wire 1 I data_to_CPU [0] $end
$var wire 1 J memory_req $end
$var wire 1 K st [3] $end
$var wire 1 L st [2] $end
$var wire 1 M st [1] $end
$var wire 1 N st [0] $end
$var wire 1 O cache_line_0 [31] $end
$var wire 1 P cache_line_0 [30] $end
$var wire 1 Q cache_line_0 [29] $end
$var wire 1 R cache_line_0 [28] $end
$var wire 1 S cache_line_0 [27] $end
$var wire 1 T cache_line_0 [26] $end
$var wire 1 U cache_line_0 [25] $end
$var wire 1 V cache_line_0 [24] $end
$var wire 1 W cache_line_0 [23] $end
$var wire 1 X cache_line_0 [22] $end
$var wire 1 Y cache_line_0 [21] $end
$var wire 1 Z cache_line_0 [20] $end
$var wire 1 [ cache_line_0 [19] $end
$var wire 1 \ cache_line_0 [18] $end
$var wire 1 ] cache_line_0 [17] $end
$var wire 1 ^ cache_line_0 [16] $end
$var wire 1 _ cache_line_0 [15] $end
$var wire 1 ` cache_line_0 [14] $end
$var wire 1 a cache_line_0 [13] $end
$var wire 1 b cache_line_0 [12] $end
$var wire 1 c cache_line_0 [11] $end
$var wire 1 d cache_line_0 [10] $end
$var wire 1 e cache_line_0 [9] $end
$var wire 1 f cache_line_0 [8] $end
$var wire 1 g cache_line_0 [7] $end
$var wire 1 h cache_line_0 [6] $end
$var wire 1 i cache_line_0 [5] $end
$var wire 1 j cache_line_0 [4] $end
$var wire 1 k cache_line_0 [3] $end
$var wire 1 l cache_line_0 [2] $end
$var wire 1 m cache_line_0 [1] $end
$var wire 1 n cache_line_0 [0] $end
$var wire 1 o cache_line_1 [31] $end
$var wire 1 p cache_line_1 [30] $end
$var wire 1 q cache_line_1 [29] $end
$var wire 1 r cache_line_1 [28] $end
$var wire 1 s cache_line_1 [27] $end
$var wire 1 t cache_line_1 [26] $end
$var wire 1 u cache_line_1 [25] $end
$var wire 1 v cache_line_1 [24] $end
$var wire 1 w cache_line_1 [23] $end
$var wire 1 x cache_line_1 [22] $end
$var wire 1 y cache_line_1 [21] $end
$var wire 1 z cache_line_1 [20] $end
$var wire 1 { cache_line_1 [19] $end
$var wire 1 | cache_line_1 [18] $end
$var wire 1 } cache_line_1 [17] $end
$var wire 1 ~ cache_line_1 [16] $end
$var wire 1 !! cache_line_1 [15] $end
$var wire 1 "! cache_line_1 [14] $end
$var wire 1 #! cache_line_1 [13] $end
$var wire 1 $! cache_line_1 [12] $end
$var wire 1 %! cache_line_1 [11] $end
$var wire 1 &! cache_line_1 [10] $end
$var wire 1 '! cache_line_1 [9] $end
$var wire 1 (! cache_line_1 [8] $end
$var wire 1 )! cache_line_1 [7] $end
$var wire 1 *! cache_line_1 [6] $end
$var wire 1 +! cache_line_1 [5] $end
$var wire 1 ,! cache_line_1 [4] $end
$var wire 1 -! cache_line_1 [3] $end
$var wire 1 .! cache_line_1 [2] $end
$var wire 1 /! cache_line_1 [1] $end
$var wire 1 0! cache_line_1 [0] $end
$var wire 1 1! dirty_line_0 $end
$var wire 1 2! dirty_line_1 $end

$scope task print_state $end
$upscope $end

$scope task run_fsm $end
$var reg 1 3! task_read $end
$var reg 1 4! task_write $end
$var reg 1 5! task_hit $end
$var reg 32 6! task_addr [31:0] $end
$var reg 32 7! task_data [31:0] $end
$var reg 32 8! captured_data [31:0] $end
$upscope $end

$scope module uut $end
$var parameter 4 9! ST_IDLE $end
$var parameter 4 :! ST_COMPARE $end
$var parameter 4 ;! ST_READ_HIT $end
$var parameter 4 <! ST_READ_MISS $end
$var parameter 4 =! ST_WRITE_HIT $end
$var parameter 4 >! ST_WRITE_MISS $end
$var parameter 4 ?! ST_WRITE_BACK $end
$var parameter 4 @! ST_EVICT $end
$var parameter 4 A! ST_ALLOCATE $end
$var wire 1 B! clk $end
$var wire 1 C! rst $end
$var wire 1 D! read $end
$var wire 1 E! write $end
$var wire 1 F! hit $end
$var wire 1 G! memory_ready $end
$var wire 1 H! address [31] $end
$var wire 1 I! address [30] $end
$var wire 1 J! address [29] $end
$var wire 1 K! address [28] $end
$var wire 1 L! address [27] $end
$var wire 1 M! address [26] $end
$var wire 1 N! address [25] $end
$var wire 1 O! address [24] $end
$var wire 1 P! address [23] $end
$var wire 1 Q! address [22] $end
$var wire 1 R! address [21] $end
$var wire 1 S! address [20] $end
$var wire 1 T! address [19] $end
$var wire 1 U! address [18] $end
$var wire 1 V! address [17] $end
$var wire 1 W! address [16] $end
$var wire 1 X! address [15] $end
$var wire 1 Y! address [14] $end
$var wire 1 Z! address [13] $end
$var wire 1 [! address [12] $end
$var wire 1 \! address [11] $end
$var wire 1 ]! address [10] $end
$var wire 1 ^! address [9] $end
$var wire 1 _! address [8] $end
$var wire 1 `! address [7] $end
$var wire 1 a! address [6] $end
$var wire 1 b! address [5] $end
$var wire 1 c! address [4] $end
$var wire 1 d! address [3] $end
$var wire 1 e! address [2] $end
$var wire 1 f! address [1] $end
$var wire 1 g! address [0] $end
$var wire 1 h! data_from_CPU [31] $end
$var wire 1 i! data_from_CPU [30] $end
$var wire 1 j! data_from_CPU [29] $end
$var wire 1 k! data_from_CPU [28] $end
$var wire 1 l! data_from_CPU [27] $end
$var wire 1 m! data_from_CPU [26] $end
$var wire 1 n! data_from_CPU [25] $end
$var wire 1 o! data_from_CPU [24] $end
$var wire 1 p! data_from_CPU [23] $end
$var wire 1 q! data_from_CPU [22] $end
$var wire 1 r! data_from_CPU [21] $end
$var wire 1 s! data_from_CPU [20] $end
$var wire 1 t! data_from_CPU [19] $end
$var wire 1 u! data_from_CPU [18] $end
$var wire 1 v! data_from_CPU [17] $end
$var wire 1 w! data_from_CPU [16] $end
$var wire 1 x! data_from_CPU [15] $end
$var wire 1 y! data_from_CPU [14] $end
$var wire 1 z! data_from_CPU [13] $end
$var wire 1 {! data_from_CPU [12] $end
$var wire 1 |! data_from_CPU [11] $end
$var wire 1 }! data_from_CPU [10] $end
$var wire 1 ~! data_from_CPU [9] $end
$var wire 1 !" data_from_CPU [8] $end
$var wire 1 "" data_from_CPU [7] $end
$var wire 1 #" data_from_CPU [6] $end
$var wire 1 $" data_from_CPU [5] $end
$var wire 1 %" data_from_CPU [4] $end
$var wire 1 &" data_from_CPU [3] $end
$var wire 1 '" data_from_CPU [2] $end
$var wire 1 (" data_from_CPU [1] $end
$var wire 1 )" data_from_CPU [0] $end
$var reg 1 *" memory_req $end
$var reg 1 +" cpu_ready $end
$var reg 32 ," data_to_CPU [31:0] $end
$var reg 4 -" st [3:0] $end
$var reg 4 ." st_next [3:0] $end
$var wire 1 /" idx $end
$upscope $end
$upscope $end
$enddefinitions $end
#0
$dumpvars
0!
0"
0#
0$
0%
0&
b0 '
b0 (
0*"
0+"
b0 ,"
bx -"
b0 ."
x3!
x4!
x5!
bx 6!
bx 7!
bx 8!
b0 9!
b1 :!
b10 ;!
b11 <!
b100 =!
b101 >!
b110 ?!
b111 @!
b1000 A!
0)
0I
0H
0G
0F
0E
0D
0C
0B
0A
0@
0?
0>
0=
0<
0;
0:
09
08
07
06
05
04
03
02
01
00
0/
0.
0-
0,
0+
0*
0J
xN
xM
xL
xK
0/"
xn
xm
xl
xk
xj
xi
xh
xg
xf
xe
xd
xc
xb
xa
x`
x_
x^
x]
x\
x[
xZ
xY
xX
xW
xV
xU
xT
xS
xR
xQ
xP
xO
x0!
x/!
x.!
x-!
x,!
x+!
x*!
x)!
x(!
x'!
x&!
x%!
x$!
x#!
x"!
x!!
x~
x}
x|
x{
xz
xy
xx
xw
xv
xu
xt
xs
xr
xq
xp
xo
x1!
x2!
0)"
0("
0'"
0&"
0%"
0$"
0#"
0""
0!"
0~!
0}!
0|!
0{!
0z!
0y!
0x!
0w!
0v!
0u!
0t!
0s!
0r!
0q!
0p!
0o!
0n!
0m!
0l!
0k!
0j!
0i!
0h!
0g!
0f!
0e!
0d!
0c!
0b!
0a!
0`!
0_!
0^!
0]!
0\!
0[!
0Z!
0Y!
0X!
0W!
0V!
0U!
0T!
0S!
0R!
0Q!
0P!
0O!
0N!
0M!
0L!
0K!
0J!
0I!
0H!
0G!
0F!
0E!
0D!
0C!
0B!
$end
#5
1"
1C!
b0 -"
02!
01!
0n
1m
0l
0k
0j
1i
0h
0g
0f
1e
0d
0c
0b
1a
0`
0_
1^
0]
0\
0[
1Z
0Y
0X
0W
1V
0U
0T
0S
1R
0Q
0P
0O
00!
0/!
1.!
0-!
0,!
0+!
1*!
0)!
0(!
0'!
1&!
0%!
0$!
0#!
1"!
0!!
1~
1}
0|
0{
1z
1y
0x
0w
1v
1u
0t
0s
1r
1q
0p
0o
0N
0M
0L
0K
#10
1!
1B!
#20
0!
0B!
#25
0"
0C!
#30
1!
13!
04!
15!
b10000000000000 6!
b0 7!
1B!
1#
1%
b10000000000000 '
1Z!
1D!
1F!
b1 ."
#40
0!
0B!
#50
1!
1B!
b1 -"
1N
b10 ."
#60
0!
0B!
#70
1!
1B!
b10 -"
0N
1M
b0 ."
b10001000100010010001000100010 ,"
1+"
1H
1D
1@
1<
19
15
11
1-
1)
#71
b10001000100010010001000100010 8!
#80
0!
0B!
#90
1!
1B!
b0 -"
0M
b1 ."
0+"
b0 ,"
0)
0H
0D
0@
0<
09
05
01
0-
#91
0#
0%
0D!
0F!
b0 ."
#92
05!
1#
1D!
b1 ."
#100
0!
0B!
#110
1!
1B!
b1 -"
1N
b111 ."
#120
0!
0B!
#130
1!
1B!
b111 -"
1M
1L
b1000 ."
#140
0!
0B!
#150
1!
1B!
b1000 -"
0N
0M
0L
1K
1*"
1J
#156
1&
1G!
b11 ."
#160
0!
0B!
#170
1!
1B!
b11 -"
1n
1l
1k
1j
1h
1g
1f
1d
1c
1`
1_
1\
1[
0Z
1X
1W
1U
1S
0R
1Q
1O
1N
1M
0K
b0 ."
0*"
b10101011110011011110111111111111 ,"
1+"
0J
1I
1H
1G
1F
1E
1D
1C
1B
1A
1@
1?
1>
1<
1;
1:
19
17
16
13
12
11
10
1.
1,
1*
1)
#171
b10101011110011011110111111111111 8!
0&
0G!
b11 ."
b0 ."
#180
0!
0B!
#190
1!
1B!
b0 -"
0N
0M
b1 ."
0+"
b0 ,"
0)
0I
0H
0G
0F
0E
0D
0C
0B
0A
0@
0?
0>
0<
0;
0:
09
07
06
03
02
01
00
0.
0,
0*
#191
0#
0D!
b0 ."
#192
03!
14!
15!
b10000000000100 6!
b11011110101011011011111011101111 7!
1$
1%
b10000000000100 '
b11011110101011011011111011101111 (
1)"
1("
1'"
1&"
1$"
1#"
1""
1~!
1}!
1|!
1{!
1z!
1x!
1w!
1u!
1t!
1r!
1p!
1n!
1m!
1l!
1k!
1i!
1h!
1e!
1E!
1F!
1/"
b1 ."
#200
0!
0B!
#210
1!
1B!
b1 -"
1N
b100 ."
#220
0!
0B!
#230
1!
1B!
b100 -"
0N
1L
12!
b0 ."
1+"
1)
#240
0!
0B!
#250
1!
1B!
b0 -"
10!
1/!
1-!
1+!
1)!
1'!
1%!
1$!
1#!
0"!
1!!
0}
1|
1{
0z
1w
0v
1t
1s
0q
1p
1o
0L
b1 ."
0+"
0)
#251
0$
0%
0E!
0F!
b0 ."
#252
05!
b11111111111111110000000000000100 6!
b11001010111111101010111111111110 7!
1$
b11111111111111110000000000000100 '
b11001010111111101010111111111110 (
0)"
1%"
1!"
0{!
0w!
1v!
1s!
1q!
0m!
0k!
0Z!
1W!
1V!
1U!
1T!
1S!
1R!
1Q!
1P!
1O!
1N!
1M!
1L!
1K!
1J!
1I!
1H!
1E!
b1 ."
#260
0!
0B!
#270
1!
1B!
b1 -"
1N
b110 ."
#280
0!
0B!
#290
1!
1B!
b110 -"
0N
1M
1L
1*"
1J
#296
1&
1G!
b111 ."
#300
0!
0B!
#310
1!
1B!
b111 -"
1N
02!
b1000 ."
0*"
0J
#311
0&
0G!
b111 ."
b1000 ."
#320
0!
0B!
#330
1!
1B!
b1000 -"
0N
0M
0L
1K
1*"
1J
#336
1&
1G!
b101 ."
#340
0!
0B!
#350
1!
1B!
b101 -"
12!
0/!
0.!
1,!
0+!
0*!
1(!
0'!
0&!
0#!
0|
1z
0y
1v
0u
0t
0p
1N
1L
0K
b0 ."
0*"
1+"
0J
1)
#351
0&
0G!
b101 ."
b0 ."
#360
0!
0B!
#370
1!
1B!
b0 -"
00!
1/!
1.!
1+!
1*!
1'!
1&!
0$!
1#!
0~
1}
1|
1y
1x
0v
1u
0r
1p
0N
0L
b1 ."
0+"
0)
#371
0$
0E!
b0 ."
#372
13!
04!
15!
b0 7!
1#
1%
b0 (
0("
0'"
0&"
0%"
0$"
0#"
0""
0!"
0~!
0}!
0|!
0z!
0x!
0v!
0u!
0t!
0s!
0r!
0q!
0p!
0n!
0l!
0i!
0h!
1D!
1F!
b1 ."
#380
0!
0B!
#390
1!
1B!
b1 -"
1N
b10 ."
#400
0!
0B!
#410
1!
1B!
b10 -"
0N
1M
b0 ."
b11001010111111101010111111111110 ,"
1+"
1H
1G
1F
1E
1D
1C
1B
1A
1@
1?
1>
1<
1:
18
17
16
15
14
13
12
10
1.
1+
1*
1)
#411
b11001010111111101010111111111110 8!
#420
0!
0B!
#430
1!
1B!
b0 -"
0M
b1 ."
0+"
b0 ,"
0)
0H
0G
0F
0E
0D
0C
0B
0A
0@
0?
0>
0<
0:
08
07
06
05
04
03
02
00
0.
0+
0*
#431
0#
0%
0D!
0F!
b0 ."
#432
03!
14!
05!
b101000000000000 6!
b10010001101000101011001111000 7!
1$
b101000000000000 '
b10010001101000101011001111000 (
1&"
1%"
1$"
1#"
1~!
1}!
1{!
1y!
1u!
1s!
1r!
1n!
1k!
0e!
1[!
1Y!
0W!
0V!
0U!
0T!
0S!
0R!
0Q!
0P!
0O!
0N!
0M!
0L!
0K!
0J!
0I!
0H!
1E!
0/"
b1 ."
#440
0!
0B!
#450
1!
1B!
b1 -"
1N
b111 ."
#460
0!
0B!
#470
1!
1B!
b111 -"
1M
1L
b1000 ."
#480
0!
0B!
#490
1!
1B!
b1000 -"
0N
0M
0L
1K
1*"
1J
#496
1&
1G!
b101 ."
#500
0!
0B!
#510
1!
1B!
b101 -"
1N
1L
0K
11!
b0 ."
0*"
1+"
0J
1)
#511
0&
0G!
b101 ."
b0 ."
#520
0!
0B!
#530
1!
1B!
b0 -"
0n
0m
0l
0g
0f
0c
1b
0a
0_
0^
0[
1Z
1Y
0X
0W
0V
0S
1R
0Q
0O
0N
0L
b1 ."
0+"
0)
#531
0$
0E!
b0 ."
#532
13!
04!
15!
b0 7!
1#
1%
b0 (
0&"
0%"
0$"
0#"
0~!
0}!
0{!
0y!
0u!
0s!
0r!
0n!
0k!
1D!
1F!
b1 ."
#540
0!
0B!
#550
1!
1B!
b1 -"
1N
b10 ."
#560
0!
0B!
#570
1!
1B!
b10 -"
0N
1M
b0 ."
b10010001101000101011001111000 ,"
1+"
1F
1E
1D
1C
1@
1?
1=
1;
17
15
14
10
1-
1)
#571
b10010001101000101011001111000 8!
#580
0!
0B!
#590
1!
1B!
b0 -"
0M
b1 ."
0+"
b0 ,